<?xml version="1.0" encoding="ISO-8859-1"?>
<MER>
	<Informacoes>
		<Posicao Left="0" Top="0"/>
		<TotalItens Valor="131"/>
		<Tipo Valor="CONCEITUAL"/>
		<Versao Valor="2.0.0"/>
		<Autor Valor=""/>
		<Observacao Valor=""/>
		<Template>
      <CAMPOS/>
      <TIPOS/>
      <COMPLEMENTO_CAMPOS/>
      <COMPLEMENTO_TABELAS/>
      <DDL>
        <CTab_A>CREATE TABLE *$nome_tabela</CTab_A>
        <CTab_B> (</CTab_B>
        <CTab_Compl>*$compl_tabela</CTab_Compl>
        <CTab_C>)*$separador*$\n</CTab_C>
        <CCamp>*$nome_campo *$tipo_campo *$compl_campo</CCamp>
        <Pk_inTab>-1</Pk_inTab>
        <Fk_inTab>-1</Fk_inTab>
        <Const_Nomear>0</Const_Nomear>
        <CConst_Nome>*$nome_tabela_*$envol_campo</CConst_Nome>
        <Separador></Separador>
      </DDL>
    </Template>
	</Informacoes>
	<Entidades>
    <Entidade nome="FUNCIONARIO" id="1">
      <Left Valor="438"/>
      <Top Valor="38"/>
      <Width Valor="102"/>
      <Height Valor="66"/>
      <Fonte default="-1"/>
      <Atributos>
        <Atributo nome="ID" id="4">
          <Left Valor="532"/>
          <Top Valor="6"/>
          <Width Valor="40"/>
          <Height Valor="16"/>
          <Fonte default="-1"/>
          <Atributos/>
          <AtributosOcultos/>
          <Dicionario></Dicionario>
          <Nula Valor="0"/>
          <Observacao></Observacao>
          <Futuro></Futuro>
          <Anexos/>
          <MaxCard Valor="1"/>
          <MinCard Valor="1"/>
          <Composto Valor="0"/>
          <Identificador Valor="-1"/>
          <Tipo Valor="Texto(1)"/>
          <Multivalorado Valor="0"/>
          <Orientacao Valor="2"/>
          <TamAuto Valor="-1"/>
          <Desvio Valor="10"/>
          <BarraID Valor="5"/>
          <Ligacoes>
            <Ligacao Destino_ID="1">
              <MostraCardinalidade Valor="0" Card_id="6"/>
              <Cardinalidades Cardinalidade="4"/>
              <Orientacao Valor="0"/>
              <Fraca Valor="0"/>
            </Ligacao>
          </Ligacoes>
        </Atributo>
        <Atributo nome="SENHA" id="7">
          <Left Valor="393"/>
          <Top Valor="10"/>
          <Width Valor="63"/>
          <Height Valor="16"/>
          <Fonte default="-1"/>
          <Atributos/>
          <AtributosOcultos/>
          <Dicionario></Dicionario>
          <Nula Valor="0"/>
          <Observacao></Observacao>
          <Futuro></Futuro>
          <Anexos/>
          <MaxCard Valor="1"/>
          <MinCard Valor="1"/>
          <Composto Valor="0"/>
          <Identificador Valor="0"/>
          <Tipo Valor="Texto(1)"/>
          <Multivalorado Valor="0"/>
          <Orientacao Valor="2"/>
          <TamAuto Valor="-1"/>
          <Desvio Valor="10"/>
          <BarraID Valor="8"/>
          <Ligacoes>
            <Ligacao Destino_ID="1">
              <MostraCardinalidade Valor="0" Card_id="9"/>
              <Cardinalidades Cardinalidade="4"/>
              <Orientacao Valor="0"/>
              <Fraca Valor="0"/>
            </Ligacao>
          </Ligacoes>
        </Atributo>
        <Atributo nome="NOME" id="10">
          <Left Valor="452"/>
          <Top Valor="3"/>
          <Width Valor="58"/>
          <Height Valor="16"/>
          <Fonte default="-1"/>
          <Atributos/>
          <AtributosOcultos/>
          <Dicionario></Dicionario>
          <Nula Valor="0"/>
          <Observacao></Observacao>
          <Futuro></Futuro>
          <Anexos/>
          <MaxCard Valor="1"/>
          <MinCard Valor="1"/>
          <Composto Valor="0"/>
          <Identificador Valor="0"/>
          <Tipo Valor="Texto(1)"/>
          <Multivalorado Valor="0"/>
          <Orientacao Valor="2"/>
          <TamAuto Valor="-1"/>
          <Desvio Valor="10"/>
          <BarraID Valor="11"/>
          <Ligacoes>
            <Ligacao Destino_ID="1">
              <MostraCardinalidade Valor="0" Card_id="12"/>
              <Cardinalidades Cardinalidade="4"/>
              <Orientacao Valor="0"/>
              <Fraca Valor="0"/>
            </Ligacao>
          </Ligacoes>
        </Atributo>
      </Atributos>
      <AtributosOcultos/>
      <Dicionario></Dicionario>
      <Nula Valor="0"/>
      <Observacao></Observacao>
      <Futuro></Futuro>
      <Anexos/>
      <AutoRelacoes AutoRelacionado="0"/>
      <Especializacoes ehEsp="0"/>
    </Entidade>
    <Entidade nome="VENDA" id="2">
      <Left Valor="438"/>
      <Top Valor="323"/>
      <Width Valor="102"/>
      <Height Valor="66"/>
      <Fonte default="-1"/>
      <Atributos>
        <Atributo nome="ID" id="16">
          <Left Valor="416"/>
          <Top Valor="394"/>
          <Width Valor="40"/>
          <Height Valor="16"/>
          <Fonte default="-1"/>
          <Atributos/>
          <AtributosOcultos/>
          <Dicionario></Dicionario>
          <Nula Valor="0"/>
          <Observacao></Observacao>
          <Futuro></Futuro>
          <Anexos/>
          <MaxCard Valor="1"/>
          <MinCard Valor="1"/>
          <Composto Valor="0"/>
          <Identificador Valor="-1"/>
          <Tipo Valor="Texto(1)"/>
          <Multivalorado Valor="0"/>
          <Orientacao Valor="2"/>
          <TamAuto Valor="-1"/>
          <Desvio Valor="10"/>
          <BarraID Valor="17"/>
          <Ligacoes>
            <Ligacao Destino_ID="2">
              <MostraCardinalidade Valor="0" Card_id="18"/>
              <Cardinalidades Cardinalidade="4"/>
              <Orientacao Valor="0"/>
              <Fraca Valor="0"/>
            </Ligacao>
          </Ligacoes>
        </Atributo>
        <Atributo nome="ID_FUNCIONARIO" id="65">
          <Left Valor="508"/>
          <Top Valor="404"/>
          <Width Valor="124"/>
          <Height Valor="16"/>
          <Fonte default="-1"/>
          <Atributos/>
          <AtributosOcultos/>
          <Dicionario></Dicionario>
          <Nula Valor="0"/>
          <Observacao></Observacao>
          <Futuro></Futuro>
          <Anexos/>
          <MaxCard Valor="1"/>
          <MinCard Valor="1"/>
          <Composto Valor="0"/>
          <Identificador Valor="0"/>
          <Tipo Valor="Texto(1)"/>
          <Multivalorado Valor="0"/>
          <Orientacao Valor="3"/>
          <TamAuto Valor="-1"/>
          <Desvio Valor="10"/>
          <BarraID Valor="66"/>
          <Ligacoes>
            <Ligacao Destino_ID="2">
              <MostraCardinalidade Valor="0" Card_id="67"/>
              <Cardinalidades Cardinalidade="4"/>
              <Orientacao Valor="0"/>
              <Fraca Valor="0"/>
            </Ligacao>
          </Ligacoes>
        </Atributo>
        <Atributo nome="VALOR" id="68">
          <Left Valor="429"/>
          <Top Valor="436"/>
          <Width Valor="64"/>
          <Height Valor="16"/>
          <Fonte default="-1"/>
          <Atributos/>
          <AtributosOcultos/>
          <Dicionario></Dicionario>
          <Nula Valor="0"/>
          <Observacao></Observacao>
          <Futuro></Futuro>
          <Anexos/>
          <MaxCard Valor="1"/>
          <MinCard Valor="1"/>
          <Composto Valor="0"/>
          <Identificador Valor="0"/>
          <Tipo Valor="Texto(1)"/>
          <Multivalorado Valor="0"/>
          <Orientacao Valor="3"/>
          <TamAuto Valor="-1"/>
          <Desvio Valor="10"/>
          <BarraID Valor="69"/>
          <Ligacoes>
            <Ligacao Destino_ID="2">
              <MostraCardinalidade Valor="0" Card_id="70"/>
              <Cardinalidades Cardinalidade="4"/>
              <Orientacao Valor="0"/>
              <Fraca Valor="0"/>
            </Ligacao>
          </Ligacoes>
        </Atributo>
        <Atributo nome="DATA_VENDA" id="87">
          <Left Valor="488"/>
          <Top Valor="423"/>
          <Width Valor="101"/>
          <Height Valor="16"/>
          <Fonte default="-1"/>
          <Atributos/>
          <AtributosOcultos/>
          <Dicionario></Dicionario>
          <Nula Valor="0"/>
          <Observacao></Observacao>
          <Futuro></Futuro>
          <Anexos/>
          <MaxCard Valor="1"/>
          <MinCard Valor="1"/>
          <Composto Valor="0"/>
          <Identificador Valor="0"/>
          <Tipo Valor="Texto(1)"/>
          <Multivalorado Valor="0"/>
          <Orientacao Valor="3"/>
          <TamAuto Valor="-1"/>
          <Desvio Valor="10"/>
          <BarraID Valor="88"/>
          <Ligacoes>
            <Ligacao Destino_ID="2">
              <MostraCardinalidade Valor="0" Card_id="89"/>
              <Cardinalidades Cardinalidade="4"/>
              <Orientacao Valor="0"/>
              <Fraca Valor="0"/>
            </Ligacao>
          </Ligacoes>
        </Atributo>
      </Atributos>
      <AtributosOcultos/>
      <Dicionario></Dicionario>
      <Nula Valor="0"/>
      <Observacao></Observacao>
      <Futuro></Futuro>
      <Anexos/>
      <AutoRelacoes AutoRelacionado="0"/>
      <Especializacoes ehEsp="0"/>
    </Entidade>
    <Entidade nome="PRODUTO" id="28">
      <Left Valor="72"/>
      <Top Valor="323"/>
      <Width Valor="102"/>
      <Height Valor="66"/>
      <Fonte default="-1"/>
      <Atributos>
        <Atributo nome="ID" id="30">
          <Left Valor="114"/>
          <Top Valor="446"/>
          <Width Valor="40"/>
          <Height Valor="16"/>
          <Fonte default="-1"/>
          <Atributos/>
          <AtributosOcultos/>
          <Dicionario></Dicionario>
          <Nula Valor="0"/>
          <Observacao></Observacao>
          <Futuro></Futuro>
          <Anexos/>
          <MaxCard Valor="1"/>
          <MinCard Valor="1"/>
          <Composto Valor="0"/>
          <Identificador Valor="-1"/>
          <Tipo Valor="Texto(1)"/>
          <Multivalorado Valor="0"/>
          <Orientacao Valor="3"/>
          <TamAuto Valor="-1"/>
          <Desvio Valor="10"/>
          <BarraID Valor="31"/>
          <Ligacoes>
            <Ligacao Destino_ID="28">
              <MostraCardinalidade Valor="0" Card_id="32"/>
              <Cardinalidades Cardinalidade="4"/>
              <Orientacao Valor="0"/>
              <Fraca Valor="0"/>
            </Ligacao>
          </Ligacoes>
        </Atributo>
        <Atributo nome="NOME" id="33">
          <Left Valor="122"/>
          <Top Valor="431"/>
          <Width Valor="58"/>
          <Height Valor="16"/>
          <Fonte default="-1"/>
          <Atributos/>
          <AtributosOcultos/>
          <Dicionario></Dicionario>
          <Nula Valor="0"/>
          <Observacao></Observacao>
          <Futuro></Futuro>
          <Anexos/>
          <MaxCard Valor="1"/>
          <MinCard Valor="1"/>
          <Composto Valor="0"/>
          <Identificador Valor="0"/>
          <Tipo Valor="Texto(1)"/>
          <Multivalorado Valor="0"/>
          <Orientacao Valor="3"/>
          <TamAuto Valor="-1"/>
          <Desvio Valor="10"/>
          <BarraID Valor="34"/>
          <Ligacoes>
            <Ligacao Destino_ID="28">
              <MostraCardinalidade Valor="0" Card_id="35"/>
              <Cardinalidades Cardinalidade="4"/>
              <Orientacao Valor="0"/>
              <Fraca Valor="0"/>
            </Ligacao>
          </Ligacoes>
        </Atributo>
        <Atributo nome="PREÇO" id="46">
          <Left Valor="147"/>
          <Top Valor="415"/>
          <Width Valor="63"/>
          <Height Valor="16"/>
          <Fonte default="-1"/>
          <Atributos/>
          <AtributosOcultos/>
          <Dicionario></Dicionario>
          <Nula Valor="0"/>
          <Observacao></Observacao>
          <Futuro></Futuro>
          <Anexos/>
          <MaxCard Valor="1"/>
          <MinCard Valor="1"/>
          <Composto Valor="0"/>
          <Identificador Valor="0"/>
          <Tipo Valor="Texto(1)"/>
          <Multivalorado Valor="0"/>
          <Orientacao Valor="3"/>
          <TamAuto Valor="-1"/>
          <Desvio Valor="10"/>
          <BarraID Valor="47"/>
          <Ligacoes>
            <Ligacao Destino_ID="28">
              <MostraCardinalidade Valor="0" Card_id="48"/>
              <Cardinalidades Cardinalidade="4"/>
              <Orientacao Valor="0"/>
              <Fraca Valor="0"/>
            </Ligacao>
          </Ligacoes>
        </Atributo>
        <Atributo nome="QUANTIDADE" id="149">
          <Left Valor="8"/>
          <Top Valor="454"/>
          <Width Valor="100"/>
          <Height Valor="16"/>
          <Fonte default="-1"/>
          <Atributos/>
          <AtributosOcultos/>
          <Dicionario></Dicionario>
          <Nula Valor="0"/>
          <Observacao></Observacao>
          <Futuro></Futuro>
          <Anexos/>
          <MaxCard Valor="1"/>
          <MinCard Valor="1"/>
          <Composto Valor="0"/>
          <Identificador Valor="0"/>
          <Tipo Valor="Texto(1)"/>
          <Multivalorado Valor="0"/>
          <Orientacao Valor="2"/>
          <TamAuto Valor="-1"/>
          <Desvio Valor="10"/>
          <BarraID Valor="150"/>
          <Ligacoes>
            <Ligacao Destino_ID="28">
              <MostraCardinalidade Valor="0" Card_id="151"/>
              <Cardinalidades Cardinalidade="4"/>
              <Orientacao Valor="0"/>
              <Fraca Valor="0"/>
            </Ligacao>
          </Ligacoes>
        </Atributo>
      </Atributos>
      <AtributosOcultos/>
      <Dicionario></Dicionario>
      <Nula Valor="0"/>
      <Observacao></Observacao>
      <Futuro></Futuro>
      <Anexos/>
      <AutoRelacoes AutoRelacionado="0"/>
      <Especializacoes ehEsp="0"/>
    </Entidade>
    <Entidade nome="CAIXA" id="52">
      <Left Valor="896"/>
      <Top Valor="322"/>
      <Width Valor="102"/>
      <Height Valor="66"/>
      <Fonte default="-1"/>
      <Atributos>
        <Atributo nome="ID" id="53">
          <Left Valor="1033"/>
          <Top Valor="315"/>
          <Width Valor="40"/>
          <Height Valor="16"/>
          <Fonte default="-1"/>
          <Atributos/>
          <AtributosOcultos/>
          <Dicionario></Dicionario>
          <Nula Valor="0"/>
          <Observacao></Observacao>
          <Futuro></Futuro>
          <Anexos/>
          <MaxCard Valor="1"/>
          <MinCard Valor="1"/>
          <Composto Valor="0"/>
          <Identificador Valor="-1"/>
          <Tipo Valor="Texto(1)"/>
          <Multivalorado Valor="0"/>
          <Orientacao Valor="3"/>
          <TamAuto Valor="-1"/>
          <Desvio Valor="10"/>
          <BarraID Valor="54"/>
          <Ligacoes>
            <Ligacao Destino_ID="52">
              <MostraCardinalidade Valor="0" Card_id="55"/>
              <Cardinalidades Cardinalidade="4"/>
              <Orientacao Valor="0"/>
              <Fraca Valor="0"/>
            </Ligacao>
          </Ligacoes>
        </Atributo>
        <Atributo nome="ID_FUNCIONARIO" id="56">
          <Left Valor="1033"/>
          <Top Valor="373"/>
          <Width Valor="124"/>
          <Height Valor="16"/>
          <Fonte default="-1"/>
          <Atributos/>
          <AtributosOcultos/>
          <Dicionario></Dicionario>
          <Nula Valor="0"/>
          <Observacao></Observacao>
          <Futuro></Futuro>
          <Anexos/>
          <MaxCard Valor="1"/>
          <MinCard Valor="1"/>
          <Composto Valor="0"/>
          <Identificador Valor="0"/>
          <Tipo Valor="Texto(1)"/>
          <Multivalorado Valor="0"/>
          <Orientacao Valor="3"/>
          <TamAuto Valor="-1"/>
          <Desvio Valor="10"/>
          <BarraID Valor="57"/>
          <Ligacoes>
            <Ligacao Destino_ID="52">
              <MostraCardinalidade Valor="0" Card_id="58"/>
              <Cardinalidades Cardinalidade="4"/>
              <Orientacao Valor="0"/>
              <Fraca Valor="0"/>
            </Ligacao>
          </Ligacoes>
        </Atributo>
        <Atributo nome="ABERTURA" id="59">
          <Left Valor="1033"/>
          <Top Valor="330"/>
          <Width Valor="87"/>
          <Height Valor="16"/>
          <Fonte default="-1"/>
          <Atributos/>
          <AtributosOcultos/>
          <Dicionario></Dicionario>
          <Nula Valor="0"/>
          <Observacao></Observacao>
          <Futuro></Futuro>
          <Anexos/>
          <MaxCard Valor="1"/>
          <MinCard Valor="1"/>
          <Composto Valor="0"/>
          <Identificador Valor="0"/>
          <Tipo Valor="Texto(1)"/>
          <Multivalorado Valor="0"/>
          <Orientacao Valor="3"/>
          <TamAuto Valor="-1"/>
          <Desvio Valor="10"/>
          <BarraID Valor="60"/>
          <Ligacoes>
            <Ligacao Destino_ID="52">
              <MostraCardinalidade Valor="0" Card_id="61"/>
              <Cardinalidades Cardinalidade="4"/>
              <Orientacao Valor="0"/>
              <Fraca Valor="0"/>
            </Ligacao>
          </Ligacoes>
        </Atributo>
        <Atributo nome="FECHAMENTO" id="62">
          <Left Valor="1033"/>
          <Top Valor="358"/>
          <Width Valor="100"/>
          <Height Valor="16"/>
          <Fonte default="-1"/>
          <Atributos/>
          <AtributosOcultos/>
          <Dicionario></Dicionario>
          <Nula Valor="0"/>
          <Observacao></Observacao>
          <Futuro></Futuro>
          <Anexos/>
          <MaxCard Valor="1"/>
          <MinCard Valor="1"/>
          <Composto Valor="0"/>
          <Identificador Valor="0"/>
          <Tipo Valor="Texto(1)"/>
          <Multivalorado Valor="0"/>
          <Orientacao Valor="3"/>
          <TamAuto Valor="-1"/>
          <Desvio Valor="10"/>
          <BarraID Valor="63"/>
          <Ligacoes>
            <Ligacao Destino_ID="52">
              <MostraCardinalidade Valor="0" Card_id="64"/>
              <Cardinalidades Cardinalidade="4"/>
              <Orientacao Valor="0"/>
              <Fraca Valor="0"/>
            </Ligacao>
          </Ligacoes>
        </Atributo>
        <Atributo nome="SALDO" id="90">
          <Left Valor="1033"/>
          <Top Valor="345"/>
          <Width Valor="64"/>
          <Height Valor="16"/>
          <Fonte default="-1"/>
          <Atributos/>
          <AtributosOcultos/>
          <Dicionario></Dicionario>
          <Nula Valor="0"/>
          <Observacao></Observacao>
          <Futuro></Futuro>
          <Anexos/>
          <MaxCard Valor="1"/>
          <MinCard Valor="1"/>
          <Composto Valor="0"/>
          <Identificador Valor="0"/>
          <Tipo Valor="Texto(1)"/>
          <Multivalorado Valor="0"/>
          <Orientacao Valor="3"/>
          <TamAuto Valor="-1"/>
          <Desvio Valor="10"/>
          <BarraID Valor="91"/>
          <Ligacoes>
            <Ligacao Destino_ID="52">
              <MostraCardinalidade Valor="0" Card_id="92"/>
              <Cardinalidades Cardinalidade="4"/>
              <Orientacao Valor="0"/>
              <Fraca Valor="0"/>
            </Ligacao>
          </Ligacoes>
        </Atributo>
      </Atributos>
      <AtributosOcultos/>
      <Dicionario></Dicionario>
      <Nula Valor="0"/>
      <Observacao></Observacao>
      <Futuro></Futuro>
      <Anexos/>
      <AutoRelacoes AutoRelacionado="0"/>
      <Especializacoes ehEsp="0"/>
    </Entidade>
    <Entidade nome="PRODUTO_VENDA_ASSOC" id="74">
      <Left Valor="244"/>
      <Top Valor="461"/>
      <Width Valor="165"/>
      <Height Valor="83"/>
      <Fonte default="-1"/>
      <Atributos>
        <Atributo nome="ID" id="75">
          <Left Valor="433"/>
          <Top Valor="471"/>
          <Width Valor="40"/>
          <Height Valor="16"/>
          <Fonte default="-1"/>
          <Atributos/>
          <AtributosOcultos/>
          <Dicionario></Dicionario>
          <Nula Valor="0"/>
          <Observacao></Observacao>
          <Futuro></Futuro>
          <Anexos/>
          <MaxCard Valor="1"/>
          <MinCard Valor="1"/>
          <Composto Valor="0"/>
          <Identificador Valor="-1"/>
          <Tipo Valor="Texto(1)"/>
          <Multivalorado Valor="0"/>
          <Orientacao Valor="3"/>
          <TamAuto Valor="-1"/>
          <Desvio Valor="10"/>
          <BarraID Valor="76"/>
          <Ligacoes>
            <Ligacao Destino_ID="74">
              <MostraCardinalidade Valor="0" Card_id="77"/>
              <Cardinalidades Cardinalidade="4"/>
              <Orientacao Valor="0"/>
              <Fraca Valor="0"/>
            </Ligacao>
          </Ligacoes>
        </Atributo>
        <Atributo nome="ID_PRODUTO" id="78">
          <Left Valor="432"/>
          <Top Valor="512"/>
          <Width Valor="101"/>
          <Height Valor="16"/>
          <Fonte default="-1"/>
          <Atributos/>
          <AtributosOcultos/>
          <Dicionario></Dicionario>
          <Nula Valor="0"/>
          <Observacao></Observacao>
          <Futuro></Futuro>
          <Anexos/>
          <MaxCard Valor="1"/>
          <MinCard Valor="1"/>
          <Composto Valor="0"/>
          <Identificador Valor="0"/>
          <Tipo Valor="Texto(1)"/>
          <Multivalorado Valor="0"/>
          <Orientacao Valor="3"/>
          <TamAuto Valor="-1"/>
          <Desvio Valor="10"/>
          <BarraID Valor="79"/>
          <Ligacoes>
            <Ligacao Destino_ID="74">
              <MostraCardinalidade Valor="0" Card_id="80"/>
              <Cardinalidades Cardinalidade="4"/>
              <Orientacao Valor="0"/>
              <Fraca Valor="0"/>
            </Ligacao>
          </Ligacoes>
        </Atributo>
        <Atributo nome="ID_VENDA" id="81">
          <Left Valor="433"/>
          <Top Valor="491"/>
          <Width Valor="83"/>
          <Height Valor="16"/>
          <Fonte default="-1"/>
          <Atributos/>
          <AtributosOcultos/>
          <Dicionario></Dicionario>
          <Nula Valor="0"/>
          <Observacao></Observacao>
          <Futuro></Futuro>
          <Anexos/>
          <MaxCard Valor="1"/>
          <MinCard Valor="1"/>
          <Composto Valor="0"/>
          <Identificador Valor="0"/>
          <Tipo Valor="Texto(1)"/>
          <Multivalorado Valor="0"/>
          <Orientacao Valor="3"/>
          <TamAuto Valor="-1"/>
          <Desvio Valor="10"/>
          <BarraID Valor="82"/>
          <Ligacoes>
            <Ligacao Destino_ID="74">
              <MostraCardinalidade Valor="0" Card_id="83"/>
              <Cardinalidades Cardinalidade="4"/>
              <Orientacao Valor="0"/>
              <Fraca Valor="0"/>
            </Ligacao>
          </Ligacoes>
        </Atributo>
      </Atributos>
      <AtributosOcultos/>
      <Dicionario></Dicionario>
      <Nula Valor="0"/>
      <Observacao></Observacao>
      <Futuro></Futuro>
      <Anexos/>
      <AutoRelacoes AutoRelacionado="0"/>
      <Especializacoes ehEsp="0"/>
    </Entidade>
    <Entidade nome="VENDA_CAIXA_ASSOC" id="99">
      <Left Valor="640"/>
      <Top Valor="445"/>
      <Width Valor="165"/>
      <Height Valor="83"/>
      <Fonte default="-1"/>
      <Atributos>
        <Atributo nome="ID" id="109">
          <Left Valor="840"/>
          <Top Valor="456"/>
          <Width Valor="40"/>
          <Height Valor="16"/>
          <Fonte default="-1"/>
          <Atributos/>
          <AtributosOcultos/>
          <Dicionario></Dicionario>
          <Nula Valor="0"/>
          <Observacao></Observacao>
          <Futuro></Futuro>
          <Anexos/>
          <MaxCard Valor="1"/>
          <MinCard Valor="1"/>
          <Composto Valor="0"/>
          <Identificador Valor="-1"/>
          <Tipo Valor="Texto(1)"/>
          <Multivalorado Valor="0"/>
          <Orientacao Valor="3"/>
          <TamAuto Valor="-1"/>
          <Desvio Valor="10"/>
          <BarraID Valor="110"/>
          <Ligacoes>
            <Ligacao Destino_ID="99">
              <MostraCardinalidade Valor="0" Card_id="111"/>
              <Cardinalidades Cardinalidade="4"/>
              <Orientacao Valor="0"/>
              <Fraca Valor="0"/>
            </Ligacao>
          </Ligacoes>
        </Atributo>
        <Atributo nome="ID_CAIXA" id="112">
          <Left Valor="840"/>
          <Top Valor="496"/>
          <Width Valor="82"/>
          <Height Valor="16"/>
          <Fonte default="-1"/>
          <Atributos/>
          <AtributosOcultos/>
          <Dicionario></Dicionario>
          <Nula Valor="0"/>
          <Observacao></Observacao>
          <Futuro></Futuro>
          <Anexos/>
          <MaxCard Valor="1"/>
          <MinCard Valor="1"/>
          <Composto Valor="0"/>
          <Identificador Valor="0"/>
          <Tipo Valor="Texto(1)"/>
          <Multivalorado Valor="0"/>
          <Orientacao Valor="3"/>
          <TamAuto Valor="-1"/>
          <Desvio Valor="10"/>
          <BarraID Valor="113"/>
          <Ligacoes>
            <Ligacao Destino_ID="99">
              <MostraCardinalidade Valor="0" Card_id="114"/>
              <Cardinalidades Cardinalidade="4"/>
              <Orientacao Valor="0"/>
              <Fraca Valor="0"/>
            </Ligacao>
          </Ligacoes>
        </Atributo>
        <Atributo nome="ID_VENDA" id="115">
          <Left Valor="840"/>
          <Top Valor="476"/>
          <Width Valor="83"/>
          <Height Valor="16"/>
          <Fonte default="-1"/>
          <Atributos/>
          <AtributosOcultos/>
          <Dicionario></Dicionario>
          <Nula Valor="0"/>
          <Observacao></Observacao>
          <Futuro></Futuro>
          <Anexos/>
          <MaxCard Valor="1"/>
          <MinCard Valor="1"/>
          <Composto Valor="0"/>
          <Identificador Valor="0"/>
          <Tipo Valor="Texto(1)"/>
          <Multivalorado Valor="0"/>
          <Orientacao Valor="3"/>
          <TamAuto Valor="-1"/>
          <Desvio Valor="10"/>
          <BarraID Valor="116"/>
          <Ligacoes>
            <Ligacao Destino_ID="99">
              <MostraCardinalidade Valor="0" Card_id="117"/>
              <Cardinalidades Cardinalidade="4"/>
              <Orientacao Valor="0"/>
              <Fraca Valor="0"/>
            </Ligacao>
          </Ligacoes>
        </Atributo>
      </Atributos>
      <AtributosOcultos/>
      <Dicionario></Dicionario>
      <Nula Valor="0"/>
      <Observacao></Observacao>
      <Futuro></Futuro>
      <Anexos/>
      <AutoRelacoes AutoRelacionado="0"/>
      <Especializacoes ehEsp="0"/>
    </Entidade>
    <Entidade nome="DESPESAS" id="210">
      <Left Valor="69"/>
      <Top Valor="152"/>
      <Width Valor="102"/>
      <Height Valor="66"/>
      <Fonte default="-1"/>
      <Atributos>
        <Atributo nome="ID" id="211">
          <Left Valor="41"/>
          <Top Valor="232"/>
          <Width Valor="40"/>
          <Height Valor="16"/>
          <Fonte default="-1"/>
          <Atributos/>
          <AtributosOcultos/>
          <Dicionario></Dicionario>
          <Nula Valor="0"/>
          <Observacao></Observacao>
          <Futuro></Futuro>
          <Anexos/>
          <MaxCard Valor="1"/>
          <MinCard Valor="1"/>
          <Composto Valor="0"/>
          <Identificador Valor="-1"/>
          <Tipo Valor="Texto(1)"/>
          <Multivalorado Valor="0"/>
          <Orientacao Valor="2"/>
          <TamAuto Valor="-1"/>
          <Desvio Valor="10"/>
          <BarraID Valor="212"/>
          <Ligacoes>
            <Ligacao Destino_ID="210">
              <MostraCardinalidade Valor="0" Card_id="213"/>
              <Cardinalidades Cardinalidade="4"/>
              <Orientacao Valor="0"/>
              <Fraca Valor="0"/>
            </Ligacao>
          </Ligacoes>
        </Atributo>
        <Atributo nome="VALOR" id="214">
          <Left Valor="146"/>
          <Top Valor="253"/>
          <Width Valor="64"/>
          <Height Valor="16"/>
          <Fonte default="-1"/>
          <Atributos/>
          <AtributosOcultos/>
          <Dicionario></Dicionario>
          <Nula Valor="0"/>
          <Observacao></Observacao>
          <Futuro></Futuro>
          <Anexos/>
          <MaxCard Valor="1"/>
          <MinCard Valor="1"/>
          <Composto Valor="0"/>
          <Identificador Valor="0"/>
          <Tipo Valor="Texto(1)"/>
          <Multivalorado Valor="0"/>
          <Orientacao Valor="3"/>
          <TamAuto Valor="-1"/>
          <Desvio Valor="10"/>
          <BarraID Valor="215"/>
          <Ligacoes>
            <Ligacao Destino_ID="210">
              <MostraCardinalidade Valor="0" Card_id="216"/>
              <Cardinalidades Cardinalidade="4"/>
              <Orientacao Valor="0"/>
              <Fraca Valor="0"/>
            </Ligacao>
          </Ligacoes>
        </Atributo>
        <Atributo nome="NOME" id="217">
          <Left Valor="89"/>
          <Top Valor="246"/>
          <Width Valor="58"/>
          <Height Valor="16"/>
          <Fonte default="-1"/>
          <Atributos/>
          <AtributosOcultos/>
          <Dicionario></Dicionario>
          <Nula Valor="0"/>
          <Observacao></Observacao>
          <Futuro></Futuro>
          <Anexos/>
          <MaxCard Valor="1"/>
          <MinCard Valor="1"/>
          <Composto Valor="0"/>
          <Identificador Valor="0"/>
          <Tipo Valor="Texto(1)"/>
          <Multivalorado Valor="0"/>
          <Orientacao Valor="3"/>
          <TamAuto Valor="-1"/>
          <Desvio Valor="10"/>
          <BarraID Valor="218"/>
          <Ligacoes>
            <Ligacao Destino_ID="210">
              <MostraCardinalidade Valor="0" Card_id="219"/>
              <Cardinalidades Cardinalidade="4"/>
              <Orientacao Valor="0"/>
              <Fraca Valor="0"/>
            </Ligacao>
          </Ligacoes>
        </Atributo>
      </Atributos>
      <AtributosOcultos/>
      <Dicionario></Dicionario>
      <Nula Valor="0"/>
      <Observacao></Observacao>
      <Futuro></Futuro>
      <Anexos/>
      <AutoRelacoes AutoRelacionado="0"/>
      <Especializacoes ehEsp="0"/>
    </Entidade>
  </Entidades>
	<Relacoes>
    <Relacao nome="REALIZA" id="13">
      <Left Valor="438"/>
      <Top Valor="184"/>
      <Width Valor="102"/>
      <Height Valor="51"/>
      <Fonte default="-1"/>
      <Atributos/>
      <AtributosOcultos/>
      <Dicionario></Dicionario>
      <Nula Valor="0"/>
      <Observacao></Observacao>
      <Futuro></Futuro>
      <Anexos/>
      <SetaDirecao Valor="2"/>
      <Ligacoes>
        <Ligacao Destino_ID="1">
          <MostraCardinalidade Valor="-1" Card_id="14"/>
          <Cardinalidades Cardinalidade="4">
            <Cardinalidade nome="" id="14">
              <Left Valor="489"/>
              <Top Valor="105"/>
              <Width Valor="40"/>
              <Height Valor="20"/>
              <Fonte default="-1"/>
              <Atributos/>
              <AtributosOcultos/>
              <Dicionario></Dicionario>
              <Nula Valor="0"/>
              <Observacao></Observacao>
              <Futuro></Futuro>
              <Anexos/>
              <Cor Valor="15780518"/>
              <TamAuto Valor="-1"/>
              <Tipo Valor="0"/>
              <TextAlin Valor="0"/>
              <Card Valor="4"/>
              <Fixa Valor="0"/>
              <Ligacoes/>
            </Cardinalidade>
          </Cardinalidades>
          <Orientacao Valor="0"/>
          <Fraca Valor="0"/>
        </Ligacao>
        <Ligacao Destino_ID="2">
          <MostraCardinalidade Valor="-1" Card_id="15"/>
          <Cardinalidades Cardinalidade="4">
            <Cardinalidade nome="" id="15">
              <Left Valor="489"/>
              <Top Valor="308"/>
              <Width Valor="40"/>
              <Height Valor="20"/>
              <Fonte default="-1"/>
              <Atributos/>
              <AtributosOcultos/>
              <Dicionario></Dicionario>
              <Nula Valor="0"/>
              <Observacao></Observacao>
              <Futuro></Futuro>
              <Anexos/>
              <Cor Valor="15780518"/>
              <TamAuto Valor="-1"/>
              <Tipo Valor="0"/>
              <TextAlin Valor="0"/>
              <Card Valor="4"/>
              <Fixa Valor="0"/>
              <Ligacoes/>
            </Cardinalidade>
          </Cardinalidades>
          <Orientacao Valor="0"/>
          <Fraca Valor="0"/>
        </Ligacao>
      </Ligacoes>
    </Relacao>
    <Relacao nome=" PERTENCE A" id="29">
      <Left Valor="258"/>
      <Top Valor="331"/>
      <Width Valor="102"/>
      <Height Valor="51"/>
      <Fonte default="-1"/>
      <Atributos/>
      <AtributosOcultos/>
      <Dicionario></Dicionario>
      <Nula Valor="0"/>
      <Observacao></Observacao>
      <Futuro></Futuro>
      <Anexos/>
      <SetaDirecao Valor="8"/>
      <Ligacoes>
        <Ligacao Destino_ID="28">
          <MostraCardinalidade Valor="-1" Card_id="36"/>
          <Cardinalidades Cardinalidade="4">
            <Cardinalidade nome="" id="36">
              <Left Valor="174"/>
              <Top Valor="341"/>
              <Width Valor="40"/>
              <Height Valor="20"/>
              <Fonte default="-1"/>
              <Atributos/>
              <AtributosOcultos/>
              <Dicionario></Dicionario>
              <Nula Valor="0"/>
              <Observacao></Observacao>
              <Futuro></Futuro>
              <Anexos/>
              <Cor Valor="15780518"/>
              <TamAuto Valor="-1"/>
              <Tipo Valor="0"/>
              <TextAlin Valor="0"/>
              <Card Valor="4"/>
              <Fixa Valor="0"/>
              <Ligacoes/>
            </Cardinalidade>
          </Cardinalidades>
          <Orientacao Valor="0"/>
          <Fraca Valor="0"/>
        </Ligacao>
        <Ligacao Destino_ID="2">
          <MostraCardinalidade Valor="-1" Card_id="37"/>
          <Cardinalidades Cardinalidade="4">
            <Cardinalidade nome="" id="37">
              <Left Valor="400"/>
              <Top Valor="341"/>
              <Width Valor="40"/>
              <Height Valor="20"/>
              <Fonte default="-1"/>
              <Atributos/>
              <AtributosOcultos/>
              <Dicionario></Dicionario>
              <Nula Valor="0"/>
              <Observacao></Observacao>
              <Futuro></Futuro>
              <Anexos/>
              <Cor Valor="15780518"/>
              <TamAuto Valor="-1"/>
              <Tipo Valor="0"/>
              <TextAlin Valor="0"/>
              <Card Valor="4"/>
              <Fixa Valor="0"/>
              <Ligacoes/>
            </Cardinalidade>
          </Cardinalidades>
          <Orientacao Valor="0"/>
          <Fraca Valor="0"/>
        </Ligacao>
      </Ligacoes>
    </Relacao>
    <Relacao nome="OPERA NO" id="93">
      <Left Valor="896"/>
      <Top Valor="48"/>
      <Width Valor="102"/>
      <Height Valor="51"/>
      <Fonte default="-1"/>
      <Atributos/>
      <AtributosOcultos/>
      <Dicionario></Dicionario>
      <Nula Valor="0"/>
      <Observacao></Observacao>
      <Futuro></Futuro>
      <Anexos/>
      <SetaDirecao Valor="3"/>
      <Ligacoes>
        <Ligacao Destino_ID="1">
          <MostraCardinalidade Valor="-1" Card_id="94"/>
          <Cardinalidades Cardinalidade="4">
            <Cardinalidade nome="" id="94">
              <Left Valor="540"/>
              <Top Valor="56"/>
              <Width Valor="40"/>
              <Height Valor="20"/>
              <Fonte default="-1"/>
              <Atributos/>
              <AtributosOcultos/>
              <Dicionario></Dicionario>
              <Nula Valor="0"/>
              <Observacao></Observacao>
              <Futuro></Futuro>
              <Anexos/>
              <Cor Valor="15780518"/>
              <TamAuto Valor="-1"/>
              <Tipo Valor="0"/>
              <TextAlin Valor="0"/>
              <Card Valor="4"/>
              <Fixa Valor="0"/>
              <Ligacoes/>
            </Cardinalidade>
          </Cardinalidades>
          <Orientacao Valor="0"/>
          <Fraca Valor="0"/>
        </Ligacao>
        <Ligacao Destino_ID="52">
          <MostraCardinalidade Valor="-1" Card_id="95"/>
          <Cardinalidades Cardinalidade="4">
            <Cardinalidade nome="" id="95">
              <Left Valor="947"/>
              <Top Valor="307"/>
              <Width Valor="40"/>
              <Height Valor="20"/>
              <Fonte default="-1"/>
              <Atributos/>
              <AtributosOcultos/>
              <Dicionario></Dicionario>
              <Nula Valor="0"/>
              <Observacao></Observacao>
              <Futuro></Futuro>
              <Anexos/>
              <Cor Valor="15780518"/>
              <TamAuto Valor="-1"/>
              <Tipo Valor="0"/>
              <TextAlin Valor="0"/>
              <Card Valor="4"/>
              <Fixa Valor="0"/>
              <Ligacoes/>
            </Cardinalidade>
          </Cardinalidades>
          <Orientacao Valor="0"/>
          <Fraca Valor="0"/>
        </Ligacao>
      </Ligacoes>
    </Relacao>
    <Relacao nome="É REGISTRADA" id="96">
      <Left Valor="648"/>
      <Top Valor="328"/>
      <Width Valor="128"/>
      <Height Valor="57"/>
      <Fonte default="-1"/>
      <Atributos/>
      <AtributosOcultos/>
      <Dicionario></Dicionario>
      <Nula Valor="0"/>
      <Observacao></Observacao>
      <Futuro></Futuro>
      <Anexos/>
      <SetaDirecao Valor="3"/>
      <Ligacoes>
        <Ligacao Destino_ID="2">
          <MostraCardinalidade Valor="-1" Card_id="97"/>
          <Cardinalidades Cardinalidade="4">
            <Cardinalidade nome="" id="97">
              <Left Valor="540"/>
              <Top Valor="341"/>
              <Width Valor="40"/>
              <Height Valor="20"/>
              <Fonte default="-1"/>
              <Atributos/>
              <AtributosOcultos/>
              <Dicionario></Dicionario>
              <Nula Valor="0"/>
              <Observacao></Observacao>
              <Futuro></Futuro>
              <Anexos/>
              <Cor Valor="15780518"/>
              <TamAuto Valor="-1"/>
              <Tipo Valor="0"/>
              <TextAlin Valor="0"/>
              <Card Valor="4"/>
              <Fixa Valor="0"/>
              <Ligacoes/>
            </Cardinalidade>
          </Cardinalidades>
          <Orientacao Valor="0"/>
          <Fraca Valor="0"/>
        </Ligacao>
        <Ligacao Destino_ID="52">
          <MostraCardinalidade Valor="-1" Card_id="98"/>
          <Cardinalidades Cardinalidade="4">
            <Cardinalidade nome="" id="98">
              <Left Valor="858"/>
              <Top Valor="340"/>
              <Width Valor="40"/>
              <Height Valor="20"/>
              <Fonte default="-1"/>
              <Atributos/>
              <AtributosOcultos/>
              <Dicionario></Dicionario>
              <Nula Valor="0"/>
              <Observacao></Observacao>
              <Futuro></Futuro>
              <Anexos/>
              <Cor Valor="15780518"/>
              <TamAuto Valor="-1"/>
              <Tipo Valor="0"/>
              <TextAlin Valor="0"/>
              <Card Valor="4"/>
              <Fixa Valor="0"/>
              <Ligacoes/>
            </Cardinalidade>
          </Cardinalidades>
          <Orientacao Valor="0"/>
          <Fraca Valor="0"/>
        </Ligacao>
      </Ligacoes>
    </Relacao>
    <Relacao nome="REGISTRA" id="220">
      <Left Valor="198"/>
      <Top Valor="46"/>
      <Width Valor="102"/>
      <Height Valor="51"/>
      <Fonte default="-1"/>
      <Atributos/>
      <AtributosOcultos/>
      <Dicionario></Dicionario>
      <Nula Valor="0"/>
      <Observacao></Observacao>
      <Futuro></Futuro>
      <Anexos/>
      <SetaDirecao Valor="2"/>
      <Ligacoes>
        <Ligacao Destino_ID="1">
          <MostraCardinalidade Valor="-1" Card_id="221"/>
          <Cardinalidades Cardinalidade="4">
            <Cardinalidade nome="" id="221">
              <Left Valor="400"/>
              <Top Valor="56"/>
              <Width Valor="40"/>
              <Height Valor="20"/>
              <Fonte default="-1"/>
              <Atributos/>
              <AtributosOcultos/>
              <Dicionario></Dicionario>
              <Nula Valor="0"/>
              <Observacao></Observacao>
              <Futuro></Futuro>
              <Anexos/>
              <Cor Valor="15780518"/>
              <TamAuto Valor="-1"/>
              <Tipo Valor="0"/>
              <TextAlin Valor="0"/>
              <Card Valor="4"/>
              <Fixa Valor="0"/>
              <Ligacoes/>
            </Cardinalidade>
          </Cardinalidades>
          <Orientacao Valor="0"/>
          <Fraca Valor="0"/>
        </Ligacao>
        <Ligacao Destino_ID="210">
          <MostraCardinalidade Valor="-1" Card_id="222"/>
          <Cardinalidades Cardinalidade="4">
            <Cardinalidade nome="" id="222">
              <Left Valor="171"/>
              <Top Valor="170"/>
              <Width Valor="40"/>
              <Height Valor="20"/>
              <Fonte default="-1"/>
              <Atributos/>
              <AtributosOcultos/>
              <Dicionario></Dicionario>
              <Nula Valor="0"/>
              <Observacao></Observacao>
              <Futuro></Futuro>
              <Anexos/>
              <Cor Valor="15780518"/>
              <TamAuto Valor="-1"/>
              <Tipo Valor="0"/>
              <TextAlin Valor="0"/>
              <Card Valor="4"/>
              <Fixa Valor="0"/>
              <Ligacoes/>
            </Cardinalidade>
          </Cardinalidades>
          <Orientacao Valor="0"/>
          <Fraca Valor="0"/>
        </Ligacao>
      </Ligacoes>
    </Relacao>
  </Relacoes>
	<EntAssoss>
	</EntAssoss>
	<Texto>
	</Texto>
</MER>
